mycalc/calcylator.py
GOEUN-0.0.1.dist-info/METADATA
GOEUN-0.0.1.dist-info/WHEEL
GOEUN-0.0.1.dist-info/top_level.txt
GOEUN-0.0.1.dist-info/RECORD
