Metadata-Version: 2.1
Name: GOEUN
Version: 0.0.1
Summary: my calculator
Home-page: https://github.com/GOEUN/mycalc
Download-URL: https://guthub.com/GOEUN/mycalc/
Author: sejinchun
License: UNKNOWN
Platform: UNKNOWN
Classifier: Programming Language :: Python :: 3
